{
  "base_experience": 149,
  "id": 51,
  "moves": [
    {
      "move": {
        "name": "scratch",
        "url": "https://pokeapi.co/api/v2/move/10/"
      },
      "version_group_details": [
        {
          "level_learned_at": 1,
          "move_learn_method": "level-up"
        }
      ]
    },
    {
      "move": {
        "name": "sand-attack",
        "url": "https://pokeapi.co/api/v2/move/28/"
      },
      "version_group_details": [
        {
          "level_learned_at": 24,
          "move_learn_method": "level-up"
        }
      ]
    },
    {
      "move": {
        "name": "body-slam",
        "url": "https://pokeapi.co/api/v2/move/34/"
      },
      "version_group_details": [
        {
          "level_learned_at": 0,
          "move_learn_method": "machine"
        }
      ]
    },
    {
      "move": {
        "name": "take-down",
        "url": "https://pokeapi.co/api/v2/move/36/"
      },
      "version_group_details": [
        {
          "level_learned_at": 0,
          "move_learn_method": "machine"
        }
      ]
    },
    {
      "move": {
        "name": "double-edge",
        "url": "https://pokeapi.co/api/v2/move/38/"
      },
      "version_group_details": [
        {
          "level_learned_at": 0,
          "move_learn_method": "machine"
        }
      ]
    },
    {
      "move": {
        "name": "growl",
        "url": "https://pokeapi.co/api/v2/move/45/"
      },
      "version_group_details": [
        {
          "level_learned_at": 1,
          "move_learn_method": "level-up"
        },
        {
          "level_learned_at": 15,
          "move_learn_method": "level-up"
        }
      ]
    },
    {
      "move": {
        "name": "growl",
        "url": "https://pokeapi.co/api/v2/move/45/"
      },
      "version_group_details": [
        {
          "level_learned_at": 1,
          "move_learn_method": "level-up"
        },
        {
          "level_learned_at": 15,
          "move_learn_method": "level-up"
        }
      ]
    },
    {
      "move": {
        "name": "hyper-beam",
        "url": "https://pokeapi.co/api/v2/move/63/"
      },
      "version_group_details": [
        {
          "level_learned_at": 0,
          "move_learn_method": "machine"
        }
      ]
    },
    {
      "move": {
        "name": "earthquake",
        "url": "https://pokeapi.co/api/v2/move/89/"
      },
      "version_group_details": [
        {
          "level_learned_at": 47,
          "move_learn_method": "level-up"
        },
        {
          "level_learned_at": 0,
          "move_learn_method": "machine"
        }
      ]
    },
    {
      "move": {
        "name": "earthquake",
        "url": "https://pokeapi.co/api/v2/move/89/"
      },
      "version_group_details": [
        {
          "level_learned_at": 47,
          "move_learn_method": "level-up"
        },
        {
          "level_learned_at": 0,
          "move_learn_method": "machine"
        }
      ]
    },
    {
      "move": {
        "name": "fissure",
        "url": "https://pokeapi.co/api/v2/move/90/"
      },
      "version_group_details": [
        {
          "level_learned_at": 0,
          "move_learn_method": "machine"
        }
      ]
    },
    {
      "move": {
        "name": "dig",
        "url": "https://pokeapi.co/api/v2/move/91/"
      },
      "version_group_details": [
        {
          "level_learned_at": 1,
          "move_learn_method": "level-up"
        },
        {
          "level_learned_at": 19,
          "move_learn_method": "level-up"
        },
        {
          "level_learned_at": 0,
          "move_learn_method": "machine"
        }
      ]
    },
    {
      "move": {
        "name": "dig",
        "url": "https://pokeapi.co/api/v2/move/91/"
      },
      "version_group_details": [
        {
          "level_learned_at": 1,
          "move_learn_method": "level-up"
        },
        {
          "level_learned_at": 19,
          "move_learn_method": "level-up"
        },
        {
          "level_learned_at": 0,
          "move_learn_method": "machine"
        }
      ]
    },
    {
      "move": {
        "name": "dig",
        "url": "https://pokeapi.co/api/v2/move/91/"
      },
      "version_group_details": [
        {
          "level_learned_at": 1,
          "move_learn_method": "level-up"
        },
        {
          "level_learned_at": 19,
          "move_learn_method": "level-up"
        },
        {
          "level_learned_at": 0,
          "move_learn_method": "machine"
        }
      ]
    },
    {
      "move": {
        "name": "toxic",
        "url": "https://pokeapi.co/api/v2/move/92/"
      },
      "version_group_details": [
        {
          "level_learned_at": 0,
          "move_learn_method": "machine"
        }
      ]
    },
    {
      "move": {
        "name": "rage",
        "url": "https://pokeapi.co/api/v2/move/99/"
      },
      "version_group_details": [
        {
          "level_learned_at": 0,
          "move_learn_method": "machine"
        }
      ]
    },
    {
      "move": {
        "name": "mimic",
        "url": "https://pokeapi.co/api/v2/move/102/"
      },
      "version_group_details": [
        {
          "level_learned_at": 0,
          "move_learn_method": "machine"
        }
      ]
    },
    {
      "move": {
        "name": "double-team",
        "url": "https://pokeapi.co/api/v2/move/104/"
      },
      "version_group_details": [
        {
          "level_learned_at": 0,
          "move_learn_method": "machine"
        }
      ]
    },
    {
      "move": {
        "name": "bide",
        "url": "https://pokeapi.co/api/v2/move/117/"
      },
      "version_group_details": [
        {
          "level_learned_at": 0,
          "move_learn_method": "machine"
        }
      ]
    },
    {
      "move": {
        "name": "rest",
        "url": "https://pokeapi.co/api/v2/move/156/"
      },
      "version_group_details": [
        {
          "level_learned_at": 0,
          "move_learn_method": "machine"
        }
      ]
    },
    {
      "move": {
        "name": "rock-slide",
        "url": "https://pokeapi.co/api/v2/move/157/"
      },
      "version_group_details": [
        {
          "level_learned_at": 0,
          "move_learn_method": "machine"
        }
      ]
    },
    {
      "move": {
        "name": "slash",
        "url": "https://pokeapi.co/api/v2/move/163/"
      },
      "version_group_details": [
        {
          "level_learned_at": 35,
          "move_learn_method": "level-up"
        }
      ]
    },
    {
      "move": {
        "name": "substitute",
        "url": "https://pokeapi.co/api/v2/move/164/"
      },
      "version_group_details": [
        {
          "level_learned_at": 0,
          "move_learn_method": "machine"
        }
      ]
    }
  ],
  "name": "dugtrio",
  "order": 84,
  "species": {
    "capture_rate": 50,
    "evolution_chain": {
      "url": "https://pokeapi.co/api/v2/evolution-chain/21/"
    },
    "growth_rate": {
      "name": "medium",
      "url": "https://pokeapi.co/api/v2/growth-rate/2/"
    },
    "habitat": {
      "name": "cave",
      "url": "https://pokeapi.co/api/v2/pokemon-habitat/1/"
    },
    "id": 51,
    "is_legendary": false,
    "is_mythical": false
  },
  "stats": [
    {
      "base_stat": 35,
      "effort": 0,
      "stat": "hp"
    },
    {
      "base_stat": 100,
      "effort": 0,
      "stat": "attack"
    },
    {
      "base_stat": 50,
      "effort": 0,
      "stat": "defense"
    },
    {
      "base_stat": 50,
      "effort": 0,
      "stat": "special-attack"
    },
    {
      "base_stat": 70,
      "effort": 0,
      "stat": "special-defense"
    },
    {
      "base_stat": 120,
      "effort": 2,
      "stat": "speed"
    }
  ],
  "types": [
    {
      "slot": 1,
      "type": "ground"
    }
  ]
}
